robloxapiwrapper
