Metadata-Version: 1.1
Name: robloxapiwrapper
Version: 0.7.5
Summary: Roblox Api Wrapper
Home-page: UNKNOWN
Author: Charlie Brasso
Author-email: charliebrasso20@gmail.com
License: MIT
Keywords: roblox
Platform: UNKNOWN
Classifier: Development Status :: 5 - Production/Stable
Classifier: Intended Audience :: Education
Classifier: Operating System :: Microsoft :: Windows :: Windows 10
Classifier: License :: OSI Approved :: MIT License
Classifier: Programming Language :: Python :: 3.7
